metadata_proxy/__init__.py
metadata_proxy/core.py
metadata_proxy/server.py
metadata_proxy/version.py
terrycain_metadata_proxy-1.5.0.dist-info/METADATA
terrycain_metadata_proxy-1.5.0.dist-info/WHEEL
terrycain_metadata_proxy-1.5.0.dist-info/entry_points.txt
terrycain_metadata_proxy-1.5.0.dist-info/top_level.txt
terrycain_metadata_proxy-1.5.0.dist-info/RECORD
