Metadata-Version: 2.1
Name: terrycain-metadata-proxy
Version: 1.5.0
Summary: AWS Metadata Proxy
Home-page: https://github.com/terrycain/metadata-proxy/
Author: Terry Cain
Author-email: terry@terrys-home.co.uk
License: UNKNOWN
Keywords: aws metadata proxy
Platform: UNKNOWN
Classifier: Development Status :: 3 - Alpha
Classifier: Framework :: AsyncIO
Classifier: License :: OSI Approved :: Apache Software License
Classifier: Intended Audience :: System Administrators
Classifier: Intended Audience :: Developers
Classifier: Topic :: Security
Classifier: Programming Language :: Python :: 3
Classifier: Programming Language :: Python :: 3.6
Classifier: Programming Language :: Python :: 3.7
Requires-Dist: aiohttp (>=3.5.4)
Requires-Dist: netifaces (>=0.10.7)
Requires-Dist: python-dateutil (>=2.7.5)
Requires-Dist: pytz (>=2019.1)
Provides-Extra: uvloop
Requires-Dist: uvloop (>=0.12.2) ; extra == 'uvloop'
